tectonic/Helpers.py
tectonic/Payments.py
tectonic/Valuation.py
tectonic/__init__.py
pytectonic-0.3.0.dist-info/LICENSE
pytectonic-0.3.0.dist-info/METADATA
pytectonic-0.3.0.dist-info/WHEEL
pytectonic-0.3.0.dist-info/top_level.txt
pytectonic-0.3.0.dist-info/RECORD
