Metadata-Version: 2.1
Name: pytectonic
Version: 0.3.0
Summary: Real Estate modeling and evaluation.
Author: Greg James
License: MIT
License-File: LICENSE
Requires-Dist: numpy (==1.24.1)
